{"links":{"static":"docs/api/fetch-client/function/json","html":"docs/api/fetch-client/function/json/index.html","fragment":"docs/api/fetch-client/function/json/index-fragment.html","self":"docs/api/fetch-client/function/json/index.json"},"name":"json","kindString":"Function","flags":{"isExported":true},"signatures":[{"name":"json","kindString":"Call signature","flags":{},"comment":{"shortText":"Create a Blob containing JSON-serialized data.\nUseful for easily creating JSON fetch request bodies.","returns":"A Blob containing the JSON serialized body.\n"},"parameters":[{"name":"body","kindString":"Parameter","flags":{},"comment":{"text":"The object to be serialized to JSON."},"type":{"type":"intrinsic","name":"any"}},{"name":"replacer","kindString":"Parameter","flags":{"isOptional":true},"comment":{"text":"The JSON.stringify replacer used when serializing."},"type":{"type":"intrinsic","name":"any"}}],"type":{"type":"reference","name":"Blob"}}],"sources":[{"fileName":"aurelia-fetch-client.d.ts","line":114,"character":28}]}