{"links":{"static":"docs/api/binding/class/AccessMember","html":"docs/api/binding/class/AccessMember/index.html","fragment":"docs/api/binding/class/AccessMember/index-fragment.html","self":"docs/api/binding/class/AccessMember/index.json"},"properties":[{"name":"name","kindString":"Property","flags":{"isExported":true},"comment":{"shortText":"The property name."},"sources":[{"fileName":"aurelia-binding.d.ts","line":464,"character":6}],"type":{"type":"intrinsic","name":"string"}},{"name":"object","kindString":"Property","flags":{"isExported":true},"comment":{"shortText":"The object expression."},"sources":[{"fileName":"aurelia-binding.d.ts","line":460,"character":8}],"type":{"type":"reference","name":"Expression","id":241}}],"methods":[{"name":"accept","kindString":"Method","flags":{"isExported":true},"signatures":[{"name":"accept","kindString":"Call signature","flags":{},"comment":{"shortText":"Accepts an expression visitor."},"parameters":[{"name":"visitor","kindString":"Parameter","flags":{},"type":{"type":"reference","name":"ExpressionVisitor","id":235}}],"type":{"type":"intrinsic","name":"void"},"inheritedFrom":{"type":"reference","name":"Expression.accept","id":255}}],"sources":[{"fileName":"aurelia-binding.d.ts","line":433,"character":8}],"inheritedFrom":{"type":"reference","name":"Expression.accept","id":255}},{"name":"assign","kindString":"Method","flags":{"isExported":true},"signatures":[{"name":"assign","kindString":"Call signature","flags":{},"comment":{"shortText":"Assigns a value to the property represented by the expression."},"parameters":[{"name":"scope","kindString":"Parameter","flags":{},"type":{"type":"reference","name":"Scope","id":5}},{"name":"value","kindString":"Parameter","flags":{},"type":{"type":"intrinsic","name":"any"}},{"name":"lookupFunctions","kindString":"Parameter","flags":{},"type":{"type":"reference","name":"LookupFunctions","id":87}}],"type":{"type":"intrinsic","name":"void"},"inheritedFrom":{"type":"reference","name":"Expression.assign","id":246}}],"sources":[{"fileName":"aurelia-binding.d.ts","line":425,"character":8}],"inheritedFrom":{"type":"reference","name":"Expression.assign","id":246}},{"name":"connect","kindString":"Method","flags":{"isExported":true},"signatures":[{"name":"connect","kindString":"Call signature","flags":{},"comment":{"shortText":"Subscribes a binding instance to the property change events along the path of the expression."},"parameters":[{"name":"binding","kindString":"Parameter","flags":{},"type":{"type":"reference","name":"Binding","id":200}},{"name":"scope","kindString":"Parameter","flags":{},"type":{"type":"reference","name":"Scope","id":5}}],"type":{"type":"intrinsic","name":"void"},"inheritedFrom":{"type":"reference","name":"Expression.connect","id":251}}],"sources":[{"fileName":"aurelia-binding.d.ts","line":429,"character":9}],"inheritedFrom":{"type":"reference","name":"Expression.connect","id":251}},{"name":"evaluate","kindString":"Method","flags":{"isExported":true},"signatures":[{"name":"evaluate","kindString":"Call signature","flags":{},"comment":{"shortText":"Evaluates the expression using the provided scope and lookup functions."},"parameters":[{"name":"scope","kindString":"Parameter","flags":{},"comment":{"text":"The scope (bindingContext + overrideContext)"},"type":{"type":"reference","name":"Scope","id":5}},{"name":"lookupFunctions","kindString":"Parameter","flags":{"isOptional":true},"comment":{"text":"Required for BindingBehavior and ValueConverter expressions.\n"},"type":{"type":"reference","name":"LookupFunctions","id":87}}],"type":{"type":"intrinsic","name":"any"},"inheritedFrom":{"type":"reference","name":"Expression.evaluate","id":242}}],"sources":[{"fileName":"aurelia-binding.d.ts","line":421,"character":10}],"inheritedFrom":{"type":"reference","name":"Expression.evaluate","id":242}}],"name":"AccessMember","kindString":"Class","flags":{"isExported":true},"comment":{"shortText":"An expression that accesses a property on an object."},"sources":[{"fileName":"aurelia-binding.d.ts","line":456,"character":33}],"extendedTypes":[{"type":"reference","name":"Expression","id":241}],"constructorMethod":{"name":"constructor","kindString":"Constructor","flags":{"isExported":true},"signatures":[{"name":"new AccessMember","kindString":"Constructor signature","flags":{},"parameters":[{"name":"object","kindString":"Parameter","flags":{},"type":{"type":"reference","name":"Expression","id":241}},{"name":"name","kindString":"Parameter","flags":{},"type":{"type":"intrinsic","name":"string"}}],"type":{"type":"reference","name":"AccessMember","id":281}}],"sources":[{"fileName":"aurelia-binding.d.ts","line":464,"character":15}]}}