{"links":{"static":"hub/docs/api/dependency-injection/class/Container/method/registerInstance","html":"hub/docs/api/dependency-injection/class/Container/method/registerInstance/index.html","fragment":"hub/docs/api/dependency-injection/class/Container/method/registerInstance/index-fragment.html","self":"hub/docs/api/dependency-injection/class/Container/method/registerInstance/index.json"},"name":"registerInstance","kindString":"Method","flags":{"isExported":true},"signatures":[{"name":"registerInstance","kindString":"Call signature","flags":{},"comment":{"shortText":"Registers an existing object instance with the container.","returns":"The resolver that was registered.\n"},"parameters":[{"name":"key","kindString":"Parameter","flags":{},"comment":{"text":"The key that identifies the dependency at resolution time; usually a constructor function."},"type":{"type":"instrinct","name":"any"}},{"name":"instance","kindString":"Parameter","flags":{"isOptional":true},"comment":{"text":"The instance that will be resolved when the key is matched. This defaults to the key value when instance is not supplied."},"type":{"type":"instrinct","name":"any"}}],"type":{"type":"reference","name":"Resolver","id":578}}],"sources":[{"fileName":"aurelia-dependency-injection.d.ts","line":401,"character":20}]}