{"links":{"static":"docs/api/router/class/RouterConfiguration/method/mapUnknownRoutes","html":"docs/api/router/class/RouterConfiguration/method/mapUnknownRoutes/index.html","fragment":"docs/api/router/class/RouterConfiguration/method/mapUnknownRoutes/index-fragment.html","self":"docs/api/router/class/RouterConfiguration/method/mapUnknownRoutes/index.json"},"name":"mapUnknownRoutes","kindString":"Method","flags":{"isExported":true},"signatures":[{"name":"mapUnknownRoutes","kindString":"Call signature","flags":{},"comment":{"shortText":"Registers an unknown route handler to be run when the URL fragment doesn't match any registered routes.","tags":[{"tag":"chainable","text":"\n"}]},"parameters":[{"name":"config","kindString":"Parameter","flags":{},"comment":{"text":"A string containing a moduleId to load, or a [[RouteConfig]], or a function that takes the\n [[NavigationInstruction]] and selects a moduleId to load."},"type":{"type":"union","types":[{"type":"instrinct","name":"string"},{"type":"reference","name":"RouteConfig","id":2084},{"type":"reflection","declaration":{"id":2262,"name":"__type","kind":65536,"kindString":"Type literal","flags":{},"signatures":[{"id":2263,"name":"__call","kind":4096,"kindString":"Call signature","flags":{},"parameters":[{"id":2264,"name":"instruction","kind":32768,"kindString":"Parameter","flags":{},"type":{"type":"reference","name":"NavigationInstruction","id":2159}}],"type":{"type":"union","types":[{"type":"instrinct","name":"string"},{"type":"reference","name":"RouteConfig","id":2084},{"type":"reference","name":"Promise","typeArguments":[{"type":"union","types":[{"type":"instrinct","name":"string"},{"type":"reference","name":"RouteConfig","id":2084}]}]}]}}],"sources":[{"fileName":"aurelia-router.d.ts","line":628,"character":49}]}}]}}],"type":{"type":"reference","name":"RouterConfiguration","id":2228}}],"sources":[{"fileName":"aurelia-router.d.ts","line":628,"character":18}]}