{"links":{"static":"hub/docs/api/templating/interface/ViewEngineHooks","html":"hub/docs/api/templating/interface/ViewEngineHooks/index.html","fragment":"hub/docs/api/templating/interface/ViewEngineHooks/index-fragment.html","self":"hub/docs/api/templating/interface/ViewEngineHooks/index.json"},"properties":[{"name":"afterCompile","kindString":"Property","flags":{"isExported":true,"isOptional":true},"comment":{"shortText":"Invoked after a template is compiled.","tags":[{"tag":"param","text":"The view factory that was produced from the compilation process.\n","param":"viewFactory"}]},"sources":[{"fileName":"aurelia-templating.d.ts","line":93,"character":14}],"type":{"type":"reflection","declaration":{"id":2538,"name":"__type","kind":65536,"kindString":"Type literal","flags":{},"signatures":[{"id":2539,"name":"__call","kind":4096,"kindString":"Call signature","flags":{},"parameters":[{"id":2540,"name":"viewFactory","kind":32768,"kindString":"Parameter","flags":{},"type":{"type":"reference","name":"ViewFactory","id":3190}}],"type":{"type":"instrinct","name":"void"}}],"sources":[{"fileName":"aurelia-templating.d.ts","line":93,"character":16}]}}},{"name":"afterCreate","kindString":"Property","flags":{"isExported":true,"isOptional":true},"comment":{"shortText":"Invoked after a view is created.","tags":[{"tag":"param","text":"The view that was created by the factory.\n","param":"view"}]},"sources":[{"fileName":"aurelia-templating.d.ts","line":108,"character":13}],"type":{"type":"reflection","declaration":{"id":2549,"name":"__type","kind":65536,"kindString":"Type literal","flags":{},"signatures":[{"id":2550,"name":"__call","kind":4096,"kindString":"Call signature","flags":{},"parameters":[{"id":2551,"name":"view","kind":32768,"kindString":"Parameter","flags":{},"type":{"type":"reference","name":"View","id":3076}}],"type":{"type":"instrinct","name":"void"}}],"sources":[{"fileName":"aurelia-templating.d.ts","line":108,"character":15}]}}},{"name":"beforeBind","kindString":"Property","flags":{"isExported":true,"isOptional":true},"comment":{"shortText":"Invoked after the bindingContext and overrideContext are configured on the view but before the view is bound.","tags":[{"tag":"param","text":"The view that was created by the factory.\n","param":"view"}]},"sources":[{"fileName":"aurelia-templating.d.ts","line":114,"character":12}],"type":{"type":"reflection","declaration":{"id":2553,"name":"__type","kind":65536,"kindString":"Type literal","flags":{},"signatures":[{"id":2554,"name":"__call","kind":4096,"kindString":"Call signature","flags":{},"parameters":[{"id":2555,"name":"view","kind":32768,"kindString":"Parameter","flags":{},"type":{"type":"reference","name":"View","id":3076}}],"type":{"type":"instrinct","name":"void"}}],"sources":[{"fileName":"aurelia-templating.d.ts","line":114,"character":14}]}}},{"name":"beforeCompile","kindString":"Property","flags":{"isExported":true,"isOptional":true},"comment":{"shortText":"Invoked before a template is compiled.","tags":[{"tag":"param","text":"The DocumentFragment to compile.","param":"content"},{"tag":"param","text":"The resources to compile the view against.","param":"resources"},{"tag":"param","text":"The compilation instruction associated with the compilation process.\n","param":"instruction"}]},"sources":[{"fileName":"aurelia-templating.d.ts","line":87,"character":15}],"type":{"type":"reflection","declaration":{"id":2532,"name":"__type","kind":65536,"kindString":"Type literal","flags":{},"signatures":[{"id":2533,"name":"__call","kind":4096,"kindString":"Call signature","flags":{},"parameters":[{"id":2534,"name":"content","kind":32768,"kindString":"Parameter","flags":{},"type":{"type":"reference","name":"DocumentFragment"}},{"id":2535,"name":"resources","kind":32768,"kindString":"Parameter","flags":{},"type":{"type":"reference","name":"ViewResources","id":3019}},{"id":2536,"name":"instruction","kind":32768,"kindString":"Parameter","flags":{},"type":{"type":"reference","name":"ViewCompileInstruction","id":2716}}],"type":{"type":"instrinct","name":"void"}}],"sources":[{"fileName":"aurelia-templating.d.ts","line":87,"character":17}]}}},{"name":"beforeCreate","kindString":"Property","flags":{"isExported":true,"isOptional":true},"comment":{"shortText":"Invoked before a view is created.","tags":[{"tag":"param","text":"The view factory that will be used to create the view.","param":"viewFactory"},{"tag":"param","text":"The DI container used during view creation.","param":"container"},{"tag":"param","text":"The cloned document fragment representing the view.","param":"content"},{"tag":"param","text":"The view creation instruction associated with this creation process.\n","param":"instruction"}]},"sources":[{"fileName":"aurelia-templating.d.ts","line":102,"character":14}],"type":{"type":"reflection","declaration":{"id":2542,"name":"__type","kind":65536,"kindString":"Type literal","flags":{},"signatures":[{"id":2543,"name":"__call","kind":4096,"kindString":"Call signature","flags":{},"parameters":[{"id":2544,"name":"viewFactory","kind":32768,"kindString":"Parameter","flags":{},"type":{"type":"reference","name":"ViewFactory","id":3190}},{"id":2545,"name":"container","kind":32768,"kindString":"Parameter","flags":{},"type":{"type":"reference","name":"Container"}},{"id":2546,"name":"content","kind":32768,"kindString":"Parameter","flags":{},"type":{"type":"reference","name":"DocumentFragment"}},{"id":2547,"name":"instruction","kind":32768,"kindString":"Parameter","flags":{},"type":{"type":"reference","name":"ViewCreateInstruction","id":2520}}],"type":{"type":"instrinct","name":"void"}}],"sources":[{"fileName":"aurelia-templating.d.ts","line":102,"character":16}]}}},{"name":"beforeUnbind","kindString":"Property","flags":{"isExported":true,"isOptional":true},"comment":{"shortText":"Invoked before the view is unbind. The bindingContext and overrideContext are still available on the view.","tags":[{"tag":"param","text":"The view that was created by the factory.\n","param":"view"}]},"sources":[{"fileName":"aurelia-templating.d.ts","line":120,"character":14}],"type":{"type":"reflection","declaration":{"id":2557,"name":"__type","kind":65536,"kindString":"Type literal","flags":{},"signatures":[{"id":2558,"name":"__call","kind":4096,"kindString":"Call signature","flags":{},"parameters":[{"id":2559,"name":"view","kind":32768,"kindString":"Parameter","flags":{},"type":{"type":"reference","name":"View","id":3076}}],"type":{"type":"instrinct","name":"void"}}],"sources":[{"fileName":"aurelia-templating.d.ts","line":120,"character":16}]}}}],"methods":[],"name":"ViewEngineHooks","kindString":"Interface","flags":{"isExported":true},"comment":{"shortText":"View engine hooks that enable a view resource to provide custom processing during the compilation or creation of a view."},"sources":[{"fileName":"aurelia-templating.d.ts","line":79,"character":40}]}