{"links":{"static":"docs/api/templating/class/ViewResources/method/registerValueConverter","html":"docs/api/templating/class/ViewResources/method/registerValueConverter/index.html","fragment":"docs/api/templating/class/ViewResources/method/registerValueConverter/index-fragment.html","self":"docs/api/templating/class/ViewResources/method/registerValueConverter/index.json"},"name":"registerValueConverter","kindString":"Method","flags":{"isExported":true},"signatures":[{"name":"registerValueConverter","kindString":"Call signature","flags":{},"comment":{"shortText":"Registers a value converter."},"parameters":[{"name":"name","kindString":"Parameter","flags":{},"comment":{"text":"The name of the value converter."},"type":{"type":"intrinsic","name":"string"}},{"name":"valueConverter","kindString":"Parameter","flags":{},"comment":{"text":"The value converter instance.\n"},"type":{"type":"reference","name":"Object"}}],"type":{"type":"intrinsic","name":"void"}}],"sources":[{"fileName":"aurelia-templating.d.ts","line":1038,"character":24}]}