{"links":{"static":"docs/api/templating/class/ViewSlot/method/removeMany","html":"docs/api/templating/class/ViewSlot/method/removeMany/index.html","fragment":"docs/api/templating/class/ViewSlot/method/removeMany/index-fragment.html","self":"docs/api/templating/class/ViewSlot/method/removeMany/index.json"},"name":"removeMany","kindString":"Method","flags":{"isExported":true},"signatures":[{"name":"removeMany","kindString":"Call signature","flags":{},"comment":{"shortText":"Removes many views from the slot.","returns":"May return a promise if the view removal triggered an animation.\n"},"parameters":[{"name":"viewsToRemove","kindString":"Parameter","flags":{},"comment":{"text":"The array of views to remove."},"type":{"type":"reference","isArray":true,"name":"View","id":3100}},{"name":"returnToCache","kindString":"Parameter","flags":{"isOptional":true},"comment":{"text":"Should the views be returned to the view cache?"},"type":{"type":"instrinct","name":"boolean"}},{"name":"skipAnimation","kindString":"Parameter","flags":{"isOptional":true},"comment":{"text":"Should the removal animation be skipped?"},"type":{"type":"instrinct","name":"boolean"}}],"type":{"type":"union","types":[{"type":"instrinct","name":"void"},{"type":"reference","name":"Promise","typeArguments":[{"type":"reference","name":"View","id":3100}]}]}}],"sources":[{"fileName":"aurelia-templating.d.ts","line":1257,"character":12}]}